my_unique_xiaoming_package/__init__.py
my_unique_xiaoming_package/example.py
my_unique_xiaoming_package-0.1.1.dist-info/METADATA
my_unique_xiaoming_package-0.1.1.dist-info/WHEEL
my_unique_xiaoming_package-0.1.1.dist-info/RECORD
