Metadata-Version: 2.1
Name: my-unique-xiaoming-package
Version: 0.1.1
Summary: 
Author: xiaoming
Author-email: lininruc@gmail.com
Requires-Python: >=3.11,<4.0
Classifier: Programming Language :: Python :: 3
Classifier: Programming Language :: Python :: 3.11
Classifier: Programming Language :: Python :: 3.12
Requires-Dist: requests (>=2.32.3,<3.0.0)
